[
  {
    "index": "dragonborn",
    "name": "Dragonborn",
    "ability_bonuses": [
      {
        "ability_score": {
          "index": "str",
          "name": "STR",
          "url": "/api/2014/ability-scores/str"
        },
        "bonus": 2
      },
      {
        "ability_score": {
          "index": "cha",
          "name": "CHA",
          "url": "/api/2014/ability-scores/cha"
        },
        "bonus": 1
      }
    ],
    "ability_bonus_options": null,
    "subrace_references": [],
    "subraces": []
  },
  {
    "index": "dwarf",
    "name": "Dwarf",
    "ability_bonuses": [
      {
        "ability_score": {
          "index": "con",
          "name": "CON",
          "url": "/api/2014/ability-scores/con"
        },
        "bonus": 2
      }
    ],
    "ability_bonus_options": null,
    "subrace_references": [
      {
        "index": "hill-dwarf",
        "name": "Hill Dwarf",
        "url": "/api/2014/subraces/hill-dwarf"
      }
    ],
    "subraces": [
      {
        "index": "hill-dwarf",
        "name": "Hill Dwarf",
        "race": {
          "index": "dwarf",
          "name": "Dwarf",
          "url": "/api/2014/races/dwarf"
        },
        "ability_bonuses": [
          {
            "ability_score": {
              "index": "wis",
              "name": "WIS",
              "url": "/api/2014/ability-scores/wis"
            },
            "bonus": 1
          }
        ]
      }
    ]
  },
  {
    "index": "elf",
    "name": "Elf",
    "ability_bonuses": [
      {
        "ability_score": {
          "index": "dex",
          "name": "DEX",
          "url": "/api/2014/ability-scores/dex"
        },
        "bonus": 2
      }
    ],
    "ability_bonus_options": null,
    "subrace_references": [
      {
        "index": "high-elf",
        "name": "High Elf",
        "url": "/api/2014/subraces/high-elf"
      }
    ],
    "subraces": [
      {
        "index": "high-elf",
        "name": "High Elf",
        "race": {
          "index": "elf",
          "name": "Elf",
          "url": "/api/2014/races/elf"
        },
        "ability_bonuses": [
          {
            "ability_score": {
              "index": "int",
              "name": "INT",
              "url": "/api/2014/ability-scores/int"
            },
            "bonus": 1
          }
        ]
      }
    ]
  },
  {
    "index": "gnome",
    "name": "Gnome",
    "ability_bonuses": [
      {
        "ability_score": {
          "index": "int",
          "name": "INT",
          "url": "/api/2014/ability-scores/int"
        },
        "bonus": 2
      }
    ],
    "ability_bonus_options": null,
    "subrace_references": [
      {
        "index": "rock-gnome",
        "name": "Rock Gnome",
        "url": "/api/2014/subraces/rock-gnome"
      }
    ],
    "subraces": [
      {
        "index": "rock-gnome",
        "name": "Rock Gnome",
        "race": {
          "index": "gnome",
          "name": "Gnome",
          "url": "/api/2014/races/gnome"
        },
        "ability_bonuses": [
          {
            "ability_score": {
              "index": "con",
              "name": "CON",
              "url": "/api/2014/ability-scores/con"
            },
            "bonus": 1
          }
        ]
      }
    ]
  },
  {
    "index": "half-elf",
    "name": "Half-Elf",
    "ability_bonuses": [
      {
        "ability_score": {
          "index": "cha",
          "name": "CHA",
          "url": "/api/2014/ability-scores/cha"
        },
        "bonus": 2
      }
    ],
    "ability_bonus_options": {
      "choose": 2,
      "from": {
        "options": [
          {
            "ability_score": {
              "index": "str",
              "name": "STR",
              "url": "/api/2014/ability-scores/str"
            },
            "bonus": 1
          },
          {
            "ability_score": {
              "index": "dex",
              "name": "DEX",
              "url": "/api/2014/ability-scores/dex"
            },
            "bonus": 1
          },
          {
            "ability_score": {
              "index": "con",
              "name": "CON",
              "url": "/api/2014/ability-scores/con"
            },
            "bonus": 1
          },
          {
            "ability_score": {
              "index": "int",
              "name": "INT",
              "url": "/api/2014/ability-scores/int"
            },
            "bonus": 1
          },
          {
            "ability_score": {
              "index": "wis",
              "name": "WIS",
              "url": "/api/2014/ability-scores/wis"
            },
            "bonus": 1
          }
        ]
      }
    },
    "subrace_references": [],
    "subraces": []
  },
  {
    "index": "half-orc",
    "name": "Half Orc",
    "ability_bonuses": [
      {
        "ability_score": {
          "index": "str",
          "name": "STR",
          "url": "/api/2014/ability-scores/str"
        },
        "bonus": 2
      },
      {
        "ability_score": {
          "index": "con",
          "name": "CON",
          "url": "/api/2014/ability-scores/con"
        },
        "bonus": 1
      }
    ],
    "ability_bonus_options": null,
    "subrace_references": [],
    "subraces": []
  },
  {
    "index": "halfling",
    "name": "Halfling",
    "ability_bonuses": [
      {
        "ability_score": {
          "index": "dex",
          "name": "DEX",
          "url": "/api/2014/ability-scores/dex"
        },
        "bonus": 2
      }
    ],
    "ability_bonus_options": null,
    "subrace_references": [
      {
        "index": "lightfoot-halfling",
        "name": "Lightfoot Halfling",
        "url": "/api/2014/subraces/lightfoot-halfling"
      }
    ],
    "subraces": [
      {
        "index": "lightfoot-halfling",
        "name": "Lightfoot Halfling",
        "race": {
          "index": "halfling",
          "name": "Halfling",
          "url": "/api/2014/races/halfling"
        },
        "ability_bonuses": [
          {
            "ability_score": {
              "index": "cha",
              "name": "CHA",
              "url": "/api/2014/ability-scores/cha"
            },
            "bonus": 1
          }
        ]
      }
    ]
  },
  {
    "index": "human",
    "name": "Human",
    "ability_bonuses": [
      {
        "ability_score": {
          "index": "str",
          "name": "STR",
          "url": "/api/2014/ability-scores/str"
        },
        "bonus": 1
      },
      {
        "ability_score": {
          "index": "dex",
          "name": "DEX",
          "url": "/api/2014/ability-scores/dex"
        },
        "bonus": 1
      },
      {
        "ability_score": {
          "index": "con",
          "name": "CON",
          "url": "/api/2014/ability-scores/con"
        },
        "bonus": 1
      },
      {
        "ability_score": {
          "index": "int",
          "name": "INT",
          "url": "/api/2014/ability-scores/int"
        },
        "bonus": 1
      },
      {
        "ability_score": {
          "index": "wis",
          "name": "WIS",
          "url": "/api/2014/ability-scores/wis"
        },
        "bonus": 1
      },
      {
        "ability_score": {
          "index": "cha",
          "name": "CHA",
          "url": "/api/2014/ability-scores/cha"
        },
        "bonus": 1
      }
    ],
    "ability_bonus_options": null,
    "subrace_references": [],
    "subraces": []
  },
  {
    "index": "tiefling",
    "name": "Tiefling",
    "ability_bonuses": [
      {
        "ability_score": {
          "index": "int",
          "name": "INT",
          "url": "/api/2014/ability-scores/int"
        },
        "bonus": 1
      },
      {
        "ability_score": {
          "index": "cha",
          "name": "CHA",
          "url": "/api/2014/ability-scores/cha"
        },
        "bonus": 2
      }
    ],
    "ability_bonus_options": null,
    "subrace_references": [],
    "subraces": []
  }
]